datacore_reporter/__init__.py
datacore_reporter/__main__.py
datacore_reporter/_version.py
datacore_reporter/client.py
datacore_reporter/request.py
datacore_reporter-0.1.0.dist-info/LICENSE.txt
datacore_reporter-0.1.0.dist-info/METADATA
datacore_reporter-0.1.0.dist-info/WHEEL
datacore_reporter-0.1.0.dist-info/entry_points.txt
datacore_reporter-0.1.0.dist-info/top_level.txt
datacore_reporter-0.1.0.dist-info/RECORD
