Metadata-Version: 2.1
Name: datacore-reporter
Version: 0.1.0
Summary: Extract data easily from your Datacore controllers.
Author-email: Sébastien Hocquet <dev@ipamo.net>
Project-URL: Homepage, https://github.com/ipamo/datacore-reporter
Project-URL: Bug Tracker, https://github.com/ipamo/datacore-reporter/issues
Keywords: datacore,symphony,san,reporter
Classifier: Development Status :: 4 - Beta
Classifier: License :: OSI Approved :: MIT License
Classifier: Operating System :: OS Independent
Classifier: Programming Language :: Python :: 3
Classifier: Environment :: Console
Classifier: Topic :: Software Development :: Libraries
Requires-Python: >=3.8
License-File: LICENSE.txt
Requires-Dist: reporter-utils
